odoo/addons/l10n_it_vat_registries_split_payment/README.rst
odoo/addons/l10n_it_vat_registries_split_payment/__init__.py
odoo/addons/l10n_it_vat_registries_split_payment/__manifest__.py
odoo/addons/l10n_it_vat_registries_split_payment/i18n/l10n_it_vat_registries_split_payment.pot
odoo/addons/l10n_it_vat_registries_split_payment/readme/CONTRIBUTORS.rst
odoo/addons/l10n_it_vat_registries_split_payment/readme/DESCRIPTION.rst
odoo/addons/l10n_it_vat_registries_split_payment/report/__init__.py
odoo/addons/l10n_it_vat_registries_split_payment/report/report_vat_registry.py
odoo/addons/l10n_it_vat_registries_split_payment/static/description/icon.png
odoo/addons/l10n_it_vat_registries_split_payment/static/description/index.html
odoo/addons/l10n_it_vat_registries_split_payment/tests/__init__.py
odoo/addons/l10n_it_vat_registries_split_payment/tests/test_sp.py
odoo11_addon_l10n_it_vat_registries_split_payment-11.0.1.0.0.99.dev4.dist-info/METADATA
odoo11_addon_l10n_it_vat_registries_split_payment-11.0.1.0.0.99.dev4.dist-info/WHEEL
odoo11_addon_l10n_it_vat_registries_split_payment-11.0.1.0.0.99.dev4.dist-info/top_level.txt
odoo11_addon_l10n_it_vat_registries_split_payment-11.0.1.0.0.99.dev4.dist-info/RECORD
